{
    "darkchocolate(morde)": 500.0,
    "darkchocolate(calibaut)": 1250.0,
    "whitechocolate(morde)": 600.0,
    "whitechocolate(calibaut)": 1500.0,
    "milkchocolate(morde)": 500.0,
    "milkchocolate(calibaut)": 1500.0,
    "apflour": 100.0,
    "bakingsoda": 50.0,
    "castorsugar": 110.0,
    "strawberrycrush": 200.0,
    "desicatedcoconut": 200.0,
    "cocoapowder": 120.0,
    "bakingpowder": 65.0,
    "pastrycreampowder": 0.0,
    "cannedcherries": 250.0,
    "nescafe": 0.0,
    "neutralglaze": 200.0,
    "peanut": 0.0,
    "walnut": 2000.0,
    "almond": 1000.0,
    "digestivebiscuit": 0.0,
    "icingsugar": 100.0,
    "foodcoloring": 0.0,
    "oreobiscuit": 0.0,
    "brownsugar": 150.0,
    "dates": 200.0,
    "dryfig": 1150.0,
    "raisins": 200.0,
    "tuttifruity": 55.0,
    "almondpowder": 1100.0,
    "gelatine": 650.0,
    "dryyeast": 300.0,
    "lotusspread": 1300.0,
    "lotusbiscuit": 1500.0,
    "ladiesfingerbiscuit": 300.0,
    "peanutbutter": 300.0,
}